perf_class/__init__.py
perf_class/perf_class.py
perf_class-1.0.5.dist-info/LICENSE
perf_class-1.0.5.dist-info/METADATA
perf_class-1.0.5.dist-info/WHEEL
perf_class-1.0.5.dist-info/entry_points.txt
perf_class-1.0.5.dist-info/top_level.txt
perf_class-1.0.5.dist-info/RECORD
