Metadata-Version: 2.1
Name: perf-class
Version: 1.0.5
Summary: A tool to mep perf script events to classes of events using regex
Home-page: https://github.com/tbarbette/perf-class
Author: Tom Barbette
Author-email: t.barbette@gmail.com
Classifier: Programming Language :: Python :: 3
Classifier: License :: OSI Approved :: MIT License
Classifier: Operating System :: OS Independent
Classifier: Topic :: System :: Operating System Kernels :: Linux
Requires-Python: >=3.6
License-File: LICENSE
